driving_gridworld/__init__.py
driving_gridworld/actions.py
driving_gridworld/car.py
driving_gridworld/gridworld.py
driving_gridworld/human_ui.py
driving_gridworld/obstacles.py
driving_gridworld/road.py
driving_gridworld-0.0.1.dist-info/METADATA
driving_gridworld-0.0.1.dist-info/RECORD
driving_gridworld-0.0.1.dist-info/WHEEL
driving_gridworld-0.0.1.dist-info/top_level.txt
