Metadata-Version: 2.1
Name: driving-gridworld
Version: 0.0.1
Summary: UNKNOWN
Home-page: UNKNOWN
Author: UNKNOWN
Author-email: UNKNOWN
License: UNKNOWN
Platform: UNKNOWN
Requires-Dist: future (==0.15.2)
Requires-Dist: setuptools (>=20.2.2)
Requires-Dist: fire
Requires-Dist: pycolab
